sor4onnx/__init__.py
sor4onnx/__main__.py
sor4onnx/onnx_opname_renamer.py
sor4onnx-1.0.7.dist-info/LICENSE
sor4onnx-1.0.7.dist-info/METADATA
sor4onnx-1.0.7.dist-info/WHEEL
sor4onnx-1.0.7.dist-info/entry_points.txt
sor4onnx-1.0.7.dist-info/top_level.txt
sor4onnx-1.0.7.dist-info/RECORD
