Metadata-Version: 2.1
Name: sor4onnx
Version: 1.0.7
Summary: Simple OP Renamer for ONNX.
Home-page: https://github.com/PINTO0309/sor4onnx
Author: Katsuya Hyodo
Author-email: rmsdh122@yahoo.co.jp
License: MIT License
Platform: linux
Platform: unix
Requires-Python: >=3.6
License-File: LICENSE
